{
  "AttributeGroups": [
    { "Name":"Org.Science",
      "Description":"Organization metadata for the Sprockets science team",
      "Tags":{"Dept":"Dept10005"},
      "Attributes":
      { "Department":"10005",
        "Active":"1",
        "ParentDept":"Research",
        "ContactAlias":"science_team@spacely.com"}
    },
    { "Name":"Org.Robotics",
      "Description":"Organization metadata for the Sprockets robotics team",
      "Tags":{"Dept":"Dept10006"},
      "Attributes":
      { "Department":"10006",
        "Active":"1","ParentDept":"Research",
        "ContactAlias":"robotics_team@spacely.com"}
    },
    { "Name":"Org.Marketing",
      "Description":"Organization metadata for the Sprockets marketing micro sites team for colonies",
      "Tags":{"Dept":"Dept80008"},
      "Attributes":
      { "Department":"80008",
        "Active":"1",
        "ParentDept":"Marketing",
        "ContactAlias":"colony_services_team@spacely.com"}
    },
    { "Name":"Org.CallCenter",
      "Description":"Organization metadata for the Sprockets marketing call center team for colonies",
      "Tags":{"Dept":"Dept80001"},
      "Attributes":
      { "Department":"80001",
        "Active":"1",
        "ParentDept":"Marketing",
        "ContactAlias":"colony_services_team@spacely.com"}
    },
    { "Name":"Org.IT",
      "Description":"Organization metadata for the Sprockets IT team",
      "Tags":{"Dept":"Dept10009"},
      "Attributes":
      { "Department":"10009",
        "Active":"1",
        "ParentDept":"Corp",
        "ContactAlias":"colony_services_team@spacely.com"}
    },
    { "Name":"Application.MarketingAnalytics.Budget",
      "Description":"An attribute group that describes the budget for a particular application",
      "Tags":{"Dept":"Dept10009"},
      "Attributes":
      { "PartnerName_ApplicationID":"12345",
        "DashboardURL": "http://partnername.com/customer-specificURL",
        "AverageMonthlyCost":"$32.50",
        "AverageDailyCost":"$1.00",
        "ProjectedMonthlyCost":"$30.00",
        "AverageCostPerDayOfWeek":
        { "Monday": "$0.50",
          "Tuesday": "$0.55",
          "Wednesday": "$0.60",
          "Thursday": "$0.70",
          "Friday": "$1.10",
          "Saturday":"$1.85",
          "Sunday":"$1.20"}
       }
      },
    { "Name":"Application.MarketingAnalytics.Core",
      "Description":"The attributes that describes the marketing analysis application",
      "Tags":{"Dept":"Dept10009"},
      "Attributes":
      { "Customer_ApplicationName":"MarketingAnalysticsApplication",
        "Customer_ApplicationID":"991538",
        "AppType":"Analytics",
        "AppCriticality": "High",
        "Runtime":"Java-12",
        "SLA":"0.1h",
        "AppRTO_minutes": "5",
        "AppLOB": "Galactic_Marketing",
        "CostCenter":"42",
        "LOB_Owner":"Zaphod Beeblebrox",
        "LOB_Title":"Chief Marketing Officer",
        "AppCodeRepo": "githubURL",
        "OnCall":
        { "PrimaryName": "Ford Prefect",
          "PrimaryPhone": "206-555-1212",
          "SecondaryName": "Arthur Dent",
          "SecondaryPhone": "312-555-1212",
          "EscalationVP": "Trillian",
          "EscalationPhone": "515-555-1212"}
        }
    },
    { "Name":"Application.MarketingAnalytics.Components",
      "Description":"MarketingAnalysisApplicationAttributes",
      "Tags":{"Dept":"Dept10009"},
      "Attributes":
      { "Customer_ApplicationID":"12345",
        "ApplicationName": "amazon.com",
        "ApplicationDescription":"My company's e-commerce site",
        "BusinessUnits":
         { "RevenueGenerating":"Yes",
           "Non-RevenueGenerating":"No"},
        "BusinessArchitecture":
         { "BusinessProcesses":"e-commerce",
           "BusinessCababilities":"list here"},
        "CustomersPartners":
         { "ProductLines":"all",
           "DigitalPlatforms":
            { "web":"Yes",
              "mobile": "Yes",
              "social": "Yes"}
         },
        "Solutions":
         { "Applications":"list here",
           "Products":"",
           "Services":"Seller Marketplace, Prime"},
         "Towers":
         { "EndUser":"",
           "Application":"",
           "Delivery":"",
           "SecurityCompliance":"",
           "ITManagement":"",
           "DataCenter":"",
           "Network":"",
           "Compute":"",
           "Storage":"",
           "Platform":"",
           "Output":""},
         "CostPools":
         { "InternalLabor":"Yes",
           "ExternalLabor":"Yes",
           "OutsideServices":"Yes",
           "Hardware":"Yes",
           "Software":"Yes",
           "FacilitiesPower":"Yes",
           "Telecom":"Yes",
           "Other":"Yes",
           "InternalServices":"Yes"}
      }
    }
  ]
}
